[{
    "Malla": {"id": "0", "nombre": "Malla vacia", "imagen":"malla-vacia.png"},
   "Marco": {"id": "0", "nombre": "Marco vacio", "imagen":"marco-vacio.png"},
    "Numeros": {"id": "0","nombre": "Numeros vacios", "imagen":"numeros-vacios.png"},
    "Agujas": {"id":"0", "nombre": "Agujas vacias", "imagen":"agujas-vacias.png"}
 },
  
{
    "Malla": {"id": "1", "nombre": "malla-roja", "imagen":"malla-roja.png"},    
    "Marco": {"id": "1", "nombre": "marco", "imagen":"marco.png"},
    "Numeros": {"id": "1","nombre": "fondo", "imagen":"numero.png"},
    "Agujas": {"id":"", "nombre": "", "imagen":""}
 },
 
{
    "Malla": {"id": "1", "nombre": "malla-violeta", "imagen":"malla.png"},
    "Marco": {"id": "1", "nombre": "marco", "imagen":"marco.png"},
    "Numeros": {"id": "1","nombre": "fondo", "imagen":"numero.png"},
    "Agujas": {"id":"", "nombre": "", "imagen":""}
 }

]

